numeralbase.py
numeralbase-1.1.dist-info/licenses/LICENSE
numeralbase-1.1.dist-info/METADATA
numeralbase-1.1.dist-info/WHEEL
numeralbase-1.1.dist-info/top_level.txt
numeralbase-1.1.dist-info/RECORD
