Metadata-Version: 2.4
Name: NumeralBase
Version: 1.1
Summary: Python library for working with different number systems
Home-page: https://github.com/TheItcor/NumeralBase
Author: Itcor
Author-email: 
Classifier: Programming Language :: Python :: 3
Classifier: Programming Language :: Python :: 3.9
Classifier: License :: OSI Approved :: MIT License
Classifier: Operating System :: OS Independent
Requires-Python: >=3.9
License-File: LICENSE
Dynamic: author
Dynamic: classifier
Dynamic: description
Dynamic: description-content-type
Dynamic: home-page
Dynamic: license-file
Dynamic: requires-python
Dynamic: summary
